zindi/__init__.py
zindi/user.py
zindi/utils.py
zindi-0.0.1b0.dist-info/METADATA
zindi-0.0.1b0.dist-info/WHEEL
zindi-0.0.1b0.dist-info/licenses/LICENSE
zindi-0.0.1b0.dist-info/RECORD
