Metadata-Version: 2.4
Name: zindi
Version: 0.0.1b0
Summary: A user-friendly ZINDI package which allow Zindians to achieve all available tasks on ZINDI Platform using this package.
Project-URL: Homepage, https://github.com/eaedk/testing-zindi-package
Project-URL: Repository, https://github.com/eaedk/testing-zindi-package.git
Author-email: The CIA TEAM & Alex Kameni <ai.team.future.coders.1@gmail.com>
License-Expression: MIT
License-File: LICENSE
Keywords: api client,competition,data science,machine learning,zindi
Classifier: Development Status :: 4 - Beta
Classifier: Intended Audience :: Developers
Classifier: Intended Audience :: Science/Research
Classifier: License :: OSI Approved :: MIT License
Classifier: Operating System :: OS Independent
Classifier: Programming Language :: Python :: 3
Classifier: Topic :: Scientific/Engineering
Classifier: Topic :: Software Development :: Libraries :: Python Modules
Requires-Python: >=3.9
Requires-Dist: pandas==2.2.3
Requires-Dist: requests-toolbelt==1.0.0
Requires-Dist: requests==2.32.3
Requires-Dist: tdqm==0.0.1
Provides-Extra: dev
Requires-Dist: autoflake; extra == 'dev'
Requires-Dist: black; extra == 'dev'
Requires-Dist: build; extra == 'dev'
Requires-Dist: bump2version; extra == 'dev'
Requires-Dist: flake8; extra == 'dev'
Requires-Dist: ipywidgets; extra == 'dev'
Requires-Dist: isort; extra == 'dev'
Requires-Dist: jupyter; extra == 'dev'
Requires-Dist: mypy; extra == 'dev'
Requires-Dist: pickleshare; extra == 'dev'
Requires-Dist: pytest; extra == 'dev'
Requires-Dist: pytest-cov; extra == 'dev'
Requires-Dist: safety; extra == 'dev'
Requires-Dist: sphinx; extra == 'dev'
Requires-Dist: tox; extra == 'dev'
Requires-Dist: twine; extra == 'dev'
Requires-Dist: wheel; extra == 'dev'
